edwin-0.2.0.dist-info/METADATA
edwin-0.2.0.dist-info/DESCRIPTION.rst
edwin-0.2.0.dist-info/RECORD
edwin-0.2.0.dist-info/metadata.json
edwin-0.2.0.dist-info/WHEEL
edwin-0.2.0.dist-info/top_level.txt
edwin/inversion.py
edwin/sampling.py
edwin/improcessing.py
edwin/optim.py
edwin/__init__.py
