Metadata-Version: 2.0
Name: edwin
Version: 0.2.0
Summary: Module related to Bayesian approach to inverse problems
Home-page: http://bitbucket.org/forieux/edwin/
Author: François Orieux
Author-email: orieux@iap.fr
License: LICENSE.txt
Platform: UNKNOWN
Classifier: Development Status :: 4 - Beta
Classifier: Intended Audience :: Developers
Classifier: License :: OSI Approved :: MIT License
Classifier: Operating System :: MacOS :: MacOS X
Classifier: Operating System :: Microsoft :: Windows
Classifier: Operating System :: POSIX
Classifier: Programming Language :: Python
Classifier: Topic :: Scientific/Engineering
Classifier: Topic :: Software Development :: Libraries
Requires-Dist: numpy (>=1.4)
